nmap_server/__init__.py
nmap_server/server.py
mcp_nmap-0.1.0.dist-info/METADATA
mcp_nmap-0.1.0.dist-info/WHEEL
mcp_nmap-0.1.0.dist-info/entry_points.txt
mcp_nmap-0.1.0.dist-info/top_level.txt
mcp_nmap-0.1.0.dist-info/RECORD
